Workbook

Sheet Export Summary
B3: This document was exported from Numbers. Each table was converted to an Excel worksheet. All other objects on each Numbers sheet were placed on separate worksheets. Please be aware that formula calculations may differ in Excel.
B7: Numbers Sheet Name | C7: Numbers Table Name | D7: Excel Worksheet Name
B9: SALES FROM TH EMONTH OF MAY
C10: SALES REPORT with EVENT SALES | D10: SALES FROM TH EMONTH OF MAY - S
B11: DAY WISE REPORT-1
C12: Table 1 | D12: DAY WISE REPORT-1 - Table 1
C13: DAILY-SALE REPORT COMPARISON | D13: DAY WISE REPORT-1 - DAILY-SALE
C14: Table 2 | D14: DAY WISE REPORT-1 - Table 2
C15: “All Drawings from the Sheet” | D15: DAY WISE REPORT-1 - Drawings
B16: TIME WISE REPORT
C17: TIME WISE SALES REPORT JUNE 2024 | D17: TIME WISE REPORT - TIME WISE SA
C18: Table 2 | D18: TIME WISE REPORT - Table 2
C19: “All Drawings from the Sheet” | D19: TIME WISE REPORT - Drawings
B20: TOP 10 BEST SELLER
C21: FOOD TOP 10 SELLER | D21: TOP 10 BEST SELLER - FOOD TOP 1
C22: DRINKS TOP 10 | D22: TOP 10 BEST SELLER - DRINKS TOP
C23: LEAST 10 SELLER RETAIL-1 | D23: TOP 10 BEST SELLER - LEAST 10 S
C24: “All Drawings from the Sheet” | D24: TOP 10 BEST SELLER - Drawings
B25: LEAST 10 SELLER-1
C26: LEAST 10 SELLER FOOD | D26: LEAST 10 SELLER-1 - LEAST 10 SE
C27: LEAST 10 SELLER DRINKS | D27: LEAST 10 SELLER-1 - LEAST 10 S1
C28: LEAST 10 SELLER RETAIL-1 | D28: LEAST 10 SELLER-1 - LEAST 10 S2
C29: “All Drawings from the Sheet” | D29: LEAST 10 SELLER-1 - Drawings
B30: SALES AND PAYMENTS DONE
C31: PROFIT AND LOSS REPORT | D31: SALES AND PAYMENTS DONE - PROFI
B32: EVENTS AND ACTIVATIONS
C33: EVENT LIST AND TOTAL | D33: EVENTS AND ACTIVATIONS - EVENT
B34: Sheet 1
C35: Table 1 | D35: Sheet 1

Sheet SALES FROM TH EMONTH OF MAY - S
B2: SALES REPORT with EVENT SALES
B3: MONTHS IN 2023 | C3: FOODS | D3: DRINKS | E3: ADD ONS | F3: TOTAL
B4: JAN | F4: {=SUM(C4:E4)} -> 0
B5: FEB | F5: {=SUM(C5:E5)} -> 0
B6: MAR | C6: 85204.76 | D6: 167386.67 | E6: 1785.71 | F6: {=SUM(C6:E6)} -> 254377.14
B7: APRIL | C7: 58493.33 | D7: 109820 | E7: 566 | F7: {=SUM(C7:E7)} -> 168879.33
B8: MAY | C8: 50057 | D8: 90270 | E8: 4248 | F8: {=SUM(C8:E8)} -> 144575
B9: JUNE | C9: 29474.29 | D9: 45245.9 | E9: 888.57 | F9: {=SUM(C9:E9)} -> 75608.76
B10: JULY | C10: 25107 | D10: 36420.95 | E10: 2765 | F10: {=SUM(C10:E10)} -> 64292.95
B11: AUG | C11: 21436.4 | D11: 49306.4 | E11: 467 | F11: {=SUM(C11:E11)} -> 71209.8
B12: SEPT | C12: 22675 | D12: 26826.52 | E12: 1966.48 | F12: {=SUM(C12:E12)} -> 51468
B13: OCT | C13: 21982 | D13: 30870.96 | E13: 2534.04 | F13: {=SUM(C13:E13)} -> 55387
B14: NOV | C14: 18863.8 | D14: 32391.89 | E14: 2249.41 | F14: {=SUM(C14:E14)} -> 53505.1
B15: DEC | F15: {=SUM(C15:E15)} -> 0
B16: TOTAL | C16: {=SUM(C4:C15)} -> 333293.58 | D16: {=SUM(D4:D15)} -> 588539.29 | E16: {=SUM(E4:E15)} -> 17470.21 | F16: {=SUM(C16:E16)} -> 939303.08

Sheet DAY WISE REPORT-1 - Table 1
A1: Table 1
A2: MONTHS IN 2023 | B2: MONDAY | C2: TUESDAY | D2: WEDNESDAY | E2: THURSDAY | F2: FRIDAY | G2: SATURDAY | H2: SUNDAY
A3: JANUARY
A4: FEBRUARY
A5: MARCH | B5: 19093 | C5: 21518 | D5: 21985 | E5: 28388 | F5: 24875 | G5: 25561 | H5: 25182
A6: APRIL | B6: 12918 | C6: 11124 | D6: 12843 | E6: 30638 | F6: 18337 | G6: 26153 | H6: 23279
A7: MAY | B7: 14932 | C7: 15167 | D7: 18017 | E7: 28373 | F7: 24315 | G7: 22503 | H7: 22348
A8: JUNE | B8: 12237 | C8: 8319 | D8: 10055 | E8: 10453 | F8: 13444 | G8: 9625 | H8: 17613
A9: JULY | B9: 10649 | C9: 9476 | D9: 9681 | E9: 7298 | F9: 11014 | G9: 13700 | H9: 11079
A10: AUGUST | B10: 6257 | C10: 5380 | D10: 7498 | E10: 6683 | F10: 7487 | G10: 10902 | H10: 6778
A11: SEPTEMBER | B11: 6024 | C11: 6712 | D11: 5508 | E11: 7825 | F11: 8303 | G11: 9667 | H11: 11783
A12: OCTOBER | B12: 9830 | C12: 9162 | D12: 6805 | E12: 7123 | F12: 6609 | G12: 7777 | H12: 5595
A13: NOVEMBER | B13: 8258 | C13: 7567 | D13: 6076 | E13: 7014 | F13: 7807 | G13: 7863 | H13: 5762
A14: DECEMBER

Sheet DAY WISE REPORT-1 - DAILY-SALE 
A1: DAILY-SALE REPORT COMPARISON
A2: TOTAL AMOUNT PER DAY | B2: Daily Sales
A3: MONDAY | B3: {=SUM('DAY WISE REPORT-1 - Table 1'!B3:B14)} -> 100198
A4: TUESDAY | B4: {=SUM('DAY WISE REPORT-1 - Table 1'!C3:C14)} -> 94425
A5: WEDNESDAY | B5: {=SUM('DAY WISE REPORT-1 - Table 1'!D3:D14)} -> 98468
A6: THURSDAY | B6: {=SUM('DAY WISE REPORT-1 - Table 1'!E3:E14)} -> 133795
A7: FRIDAY | B7: {=SUM('DAY WISE REPORT-1 - Table 1'!F3:F14)} -> 122191
A8: SATURDAY | B8: {=SUM('DAY WISE REPORT-1 - Table 1'!G3:G14)} -> 133751
A9: SUNDAY | B9: {=SUM('DAY WISE REPORT-1 - Table 1'!H3:H14)} -> 129419

Sheet DAY WISE REPORT-1 - Table 2
A1: NOTE
B2: This report will help the management to decide on which day we can have our better promotion and boost the marketing. This will also help us to drive our sales and focus on the days of business and the weakest day of the week.

Sheet DAY WISE REPORT-1 - Drawings

Sheet TIME WISE REPORT - TIME WISE SA
A1: TIME WISE SALES REPORT JUNE 2024
A2: MONTHS IN 2023 | B2: 7am - 1pm | C2: 2pm - 7pm | D2: 8pm - 1am
A3: SALES PER HOUR | B3: 21052 | C3: 28398 | D3: 27922

Sheet TIME WISE REPORT - Table 2
A1: NOTE
B2: This report indicates the hourly basis sales of the shop. This will help us to identify which part of the menu needs the biggest changes or where we can allocate more staff and support the service. The management is eager to support the timely basis of the volume of guests and food selection based on the timings.

Sheet TIME WISE REPORT - Drawings

Sheet TOP 10 BEST SELLER - FOOD TOP 1
A1: FOOD TOP 10 SELLER
B2: TOTAL VALUE SOLD
A3: VANILLA CEREAL CAKE | B3: 8360
A4: DATES PUDDING | B4: 7695
A5: CHOCOLATE MOLTEN CAKE | B5: 6520
A6: AVO ON TOAST | B6: 4702
A7: HONEY TOAST | B7: 3960

Sheet TOP 10 BEST SELLER - DRINKS TOP
A1: DRINKS TOP 10
B2: TOTAL VALUE
A3: HOT SPANISH | B3: 12362
A4: ICE V60 PASSION FRUIT | B4: 8910
A5: ICE SPANISH | B5: 7898
A6: ICE V60 ETHOPIA | B6: 7230
A7: ICE MATCHA | B7: 5981
A8: FLAT WHITE | B8: 5410
A9: HIBISCUS | B9: 4960
A10: ESPRESSO | B10: 3477
A11: AMERICANO | B11: 3402
A12: PICCOLO | B12: 2648

Sheet TOP 10 BEST SELLER - LEAST 10 S
A1: NOTE: | B1: REPORT IS TAKEN FOR THE MONTH OF
A2: This report will help the management to assess which food are best selling and which items are least selling. End reengineering is needed for us to drive more customers. And this will help to decide which Items we can see go and create new item based on the market strategy.

Sheet TOP 10 BEST SELLER - Drawings

Sheet LEAST 10 SELLER-1 - LEAST 10 SE
A1: LEAST 10 SELLER FOOD
B2: TOTAL VALUE SOLD
A3: MATCHA BOWL | B3: 1403
A4: ACAI BOWL | B4: 1534
A5: TURKISH EGG | B5: 1957
A6: CHORIZO SHAKSHUKA | B6: 2180
A7: TUNA SANDWICH | B7: 2564

Sheet LEAST 10 SELLER-1 - LEAST 10 S1
A1: LEAST 10 SELLER DRINKS
B2: TOTAL VALUE
A3: MACHIATO | B3: 198
A4: CHAMOMILE TEA | B4: 288
A5: GREEN SMOOTHIE | B5: 304
A6: ENGLISH BREAKFAST | B6: 320
A7: GREEN TEA | B7: 384
A8: HOT CHOCOLATE | B8: 570
A9: CHERRY FRAPPE | B9: 570
A10: PINK SMOOTHIE | B10: 684
A11: MATCHA FRAPPE | B11: 760
A12: V60 ETHIOPIA | B12: 810

Sheet LEAST 10 SELLER-1 - LEAST 10 S2
A2: NOTE: | B2: Drinks and Food report shows only sales made in the system. The item with 0 sales was not included to the report.

Sheet LEAST 10 SELLER-1 - Drawings

Sheet SALES AND PAYMENTS DONE - PROFI
B2: PROFIT AND LOSS REPORT
B3: SALES VS EXPENSE
B4: TOTAL SALES | C4: 72897
B5: INVENTORY ON HAND | C5: 27043.47
B6: SALARY | C6: 65294
B7: SEWA | C7: 6458
B8: ETISALAT | C8: 2200
B9: RENTALS | C9: 20000
B10: SUPPLIER PAYMENT | C10: 20234.46
B11: PETTY CASH USAGE | C11: 6779.93
B12: TOTAL: | C12: {=SUM(C4+C5)-(C6+C7+C8+C9+C10+C11)} -> -21025.92
B13: NOTE: THE COLOR OF THE TOTAL VALUE IS IN THIS COLORS | C13: RED (NEGATIVE).
C14: GREEN (POSITIVE)

Sheet EVENTS AND ACTIVATIONS - EVENT 
A1: EVENT LIST AND TOTAL
A2: EVENT NAME | B2: DATES | C2: TOTAL SALES
A3: IGCF EVENT | B3: SEPT 2 - SEPT 5 | C3: 44155 | D3: 45536
A4: JEWELRY EVENT | B4: SEPT 25 - SEPT 29 | C4: 25665
A5: PERFUME EVENT | B5: OCT 04 - OCT 13 | C5: 45271 | D5: 45566
A6: SHARJAH ECONOMIC | B6: OCT 14 - OCT 24 | C6: 15758.35
A7: DEPARTMENT OF EDUCATION | B7: OCT 28 - NOV 1 | C7: 12608
A8: BOOK FARE | B8: NOV 06 - NOV 17 | C8: 68719.8 | D8: 45597
A9: DARYA EVENT | B9: NOV 27 - NOV 30 | C9: 15100
A12: TOTAL: | C12: {=SUM(C3:C11)} -> 227277.15

Sheet Sheet 1
A1: Table 1
